Workbook

Sheet Leeme
A1: BASE DE DATOS A LLENAR · Cafeterías de especialidad en Bogotá
A2: Haciendo Economía 2026-2 · Protocolo de trabajo de campo (Entrega 3b) · v1.1 (pre-piloto)
A4: PREGUNTA (reformulada como asociación descriptiva)
A5: ¿Cómo se asocian el storytelling y la ambientación de las cafeterías de especialidad de Bogotá con su diferenciación percibida, la recordación y la preferencia declarada de sus clientes? Los datos describen asociaciones entre cafés; no miden el efecto de «implementar» una estrategia.
A7: MUESTRA Y UNIDAD DE ANÁLISIS
A8: • Meta: 10 cafés × 8 encuestas = 80 encuestas y 10 fichas de observación. Lista, direcciones y evidencia en Muestra_Cafes.
A9: • La unidad de análisis es el CAFÉ (n = 10): las 8 encuestas de cada café se resumen en promedios por café. 80 encuestas en 10 negocios no equivalen a 80 negocios; la muestra es intencional y no representa a toda Bogotá.
A10: • Zonas (las tres de la Entrega 1): Z1 Parkway–Teusaquillo (6 cafés), Z2 La Macarena (2) y Z3 Centro (2).
A11: • Criterio de especialidad (propuesta; ajústenlo): entra un local si (a) aparece como café de especialidad en al menos una fuente externa verificable (Coffee Master Colombia, Revista Diners 2023, Fondo Cultural Cafetero, SCA) o (b) vende café de origen identificado según su carta o redes, lo que se confirma en la visita. Los locales marcados «Verificar» en Muestra_Cafes deben resolverse antes de salir a campo.
A12: • Reemplazos (R1–R4): si el local no autoriza o está cerrado, se pasa a una reserva de la MISMA zona. Se registra en Muestra_Cafes (original: Reemplazado, meta 0; reserva: Pendiente, meta 8).
A14: CÓMO USAR ESTE ARCHIVO
A15: 1. Hoja Ficha_Cafe: una fila por café (observación). Hoja Encuestas: una fila por cliente (meta: 8 por café, 80 en total).
... A32: • Índices: idx_story ahora suma st1–st6 (0–6) y ambos índices quedan vacíos si falta algún ítem. Se reparó Avance (#REF!). El ejemplo ficticio del Piloto se marcó como ejemplo.

Sheet Muestra_Cafes
A1: cafe_id | B1: zona_muestreo | C1: id_mapa | D1: coordenadas | E1: nombre_cafe | F1: direccion | G1: localidad | H1: tipo_negocio | I1: responsable | J1: dia_tipo | K1: franja | L1: fecha_prevista | M1: meta_encuestas | N1: estado | O1: evidencia_especialidad | P1: fuente
A2: C01 | B2: Z1 Parkway–Teusaquillo | C2: M-01 | D2: 4.631853, -74.073582 | E2: Quipile Café de Origen | F2: Cra 24 #42-71 | G2: Teusaquillo | H2: Pequeña cadena (2–5 locales) | I2: A | J2: Entre semana | K2: Mañana (8–11) | L2: 46331 | M2: 8 | N2: Pendiente | O2: Uno de los primeros cafés de especialidad de Bogotá (12 años en el mercado); apoya a caficultores colombianos. | P2: https://fondoculturalcafetero.org/nuestros_artistas/quipile-coffee/
A3: C02 | B3: Z1 Parkway–Teusaquillo | C3: M-02 | D3: 4.628863, -74.072224 | E3: Rolo Café PW | F3: Cra 22 #40-07 | G3: Teusaquillo | H3: Independiente (1 local) | I3: B | J3: Entre semana | K3: Tarde (14–17) | L3: 46331 | M3: 8 | N3: Pendiente | O3: Entrega 1 lo describe por su ambientación (coworking, lectura) | P3: https://maps.google.com/?cid=198281915670443191
A4: C03 | B4: Z1 Parkway–Teusaquillo | C4: M-03 | D4: 4.622475, -74.070058 | E4: Bogotá Coffee Roasters LAB Cine y Café | F4: Tv 17a Bis #35-71 | G4: Teusaquillo | H4: Independiente (1 local) | I4: C | J4: Entre semana | K4: Mañana (8–11) | L4: 46331 | M4: 8 | N4: Pendiente | O4: Participante de Coffee Master Colombia; granos de origen y bebidas de autor; organizador y promotor del Coffee Master. | P4: https://www.coffeemastercolombia.com/participante/bogota-coffee-roasters-cine-cafe/
A5: C04 | B5: Z1 Parkway–Teusaquillo | C5: M-04 | D5: 4.628731, -74.075306 | E5: El Bourbon Café | F5: Cl 39 #24-36 | G5: Teusaquillo | H5: Independiente (1 local) | I5: A | J5: Entre semana | K5: Tarde (14–17) | L5: 46331 | M5: 8 | N5: Pendiente | O5: Ofrece varios métodos de preparación de café; formato mixto (tatuajes, vinilos, juegos de mesa). | P5: https://www.instagram.com/elbourbon_cafe/
A6: C05 | B6: Z1 Parkway–Teusaquillo | C6: M-05 | D6: 4.626248, -74.071168 | E6: Ezcarlata Café | F6: Cra 18 #39A-59 | G6: Teusaquillo | H6: Independiente (1 local) | I6: B | J6: Entre semana | K6: Mañana (8–11) | L6: 46331 | M6: 8 | N6: Pendiente | O6: Se presenta con especialidad en métodos de filtrado (menú en Issuu). Falta fuente externa. | P6: https://issuu.com/ezcarlatacol/docs/menu_ezcarlata
A7: C06 | B7: Z1 Parkway–Teusaquillo | C7: M-06 | D7: 4.628678, -74.075199 | E7: Orilla Tienda de Café | F7: Cl 39 #24-26 | G7: Teusaquillo | H7: Independiente (1 local) | I7: C | J7: Entre semana | K7: Tarde (14–17) | L7: 46331 | M7: 8 | N7: Pendiente | O7: Se caracteriza por su café y la cultura caficultora (Entrega 1). Falta fuente externa. | P7: https://maps.google.com/?cid=475238163965829388
A8: C07 | B8: Z2 La Macarena | C8: M-07 | D8: 4.613318, -74.067341 | E8: CatCoffee | F8: Cra. 6 #26b-61 Loc 1 | G8: Chapinero | H8: Independiente (1 local) | I8: A | J8: Entre semana | K8: Mañana (8–11) | L8: 46325 | M8: 8 | N8: Pendiente | O8: Se enfoca en ofrecer experiencias sensoriales sobre la cultura cafetera. Utilizan granos de alta calidad con los que han destacado y obtenido premios en el Coffee Master Colombia. | P8: https://www.instagram.com/catcoffeeco/?hl=es
A9: C08 | B9: Z2 La Macarena | C9: M-08 | D9: 4.616315, -74.071428 | E9: Oishii Bubble Tea At 7 Days | F9: Cl 28 #13-22 Local 50 | G9: Santa Fe | H9: Independiente (1 local) | I9: B | J9: Entre semana | K9: Tarde (14–17) | L9: 46325 | M9: 8 | N9: Pendiente | O9: Negocio mixto: té de burbujas, postres y café de especialidad estilo japonés; 4,6 estrellas en Google Maps. | P9: https://wanderboat.ai/restaurants/colombia/bogota%2C-capital-district/oishii-bubble-tea-at-7-days/6cNVwsvYRUufEI_0k1MO2w
A10: C09 | B10: Z3 Centro | C10: M-09 | D10: 4.597011, -74.076033 | E10: Arte y Pasión Café | F10: Cl 10 #8-87 | G10: La Candelaria | H10: Pequeña cadena (2–5 locales) | I10: C | J10: Entre semana | K10: Mañana (8–11) | L10: 46329 | M10: 8 | N10: Pendiente | O10: Escuela de baristas en casa colonial; se especializa en notas sensoriales | P10: https://arteypasioncafe.com/
A11: C10 | B11: Z3 Centro | C11: M-10 | D11: 4.600645, -74.073289 | E11: Nossa Café Pastel | F11: Cl 12C #7A-37 | G11: La Candelaria | H11: Independiente (1 local) | I11: A | J11: Entre semana | K11: Tarde (14–17) | L11: 46329 | M11: 8 | N11: Pendiente | O11: Pastelería y cafetería de autor que busca el maridaje café–pastel. Con café de especialidad. | P11: https://www.instagram.com/somoscafenossapastel/
A12: R1 | B12: Z1 Parkway–Teusaquillo | C12: R-01 | D12: 4.625624, -74.070087 | E12: Filtrando Café | F12: Cra. 17 #39a 8 | G12: Teusaquillo | H12: Independiente (1 local) | I12: A | J12: Fin de semana | K12: Mañana (8–11) | M12: 0 | N12: Reserva | O12: Cafeteria dedicada a cultivar la cultura cafetera en Bogotá, realizan recorridos y catas únicas en su establecimiento | P12: https://www.instagram.com/filtrandocafes/
A13: R2 | B13: Z2 La Macarena | C13: R-02 | D13: 4.615197, -74.071853 | E13: Terracota Café y Más | F13: Kr 13 #27-00 | G13: Teusaquillo | H13: Pequeña cadena (2–5 locales) | I13: B | J13: Entre semana | K13: Tarde (14–17) | M13: 0 | N13: Reserva | O13: Premiada en Coffee Master Colombia: 1.er lugar 2024, 2.º 2025 y 3.º 2026; ofrece experiencias sensoriales sobre cultura cafetera. | P13: https://terracotacafeymas.com/
A14: R3 | B14: Z3 Centro | C14: R-03 | D14: 4.598687, -74.069792 | E14: Café Nos | F14: Cl. 12d #3 15 | G14: Santa Fe | H14: Independiente (1 local) | I14: C | J14: Fin de semana | K14: Tarde (14–17) | M14: 0 | N14: Reserva | O14: Con una variedad inmensa de bebidas por probar, café nos tiene una estética minimalista, bebidas de autor. | P14: https://www.instagram.com/cafe.noscol?igsh=Z2hwYWNua2lzNnRy
M15: 0 | N15: Reserva
A17: Notas: (1) Lista tomada de las «Cafeterías de estudio» de la Entrega 1. (2) id_mapa M-01…M-10 es PROVISIONAL: reemplácelo por el ID del shapefile de la Entrega 3a; la dirección va en su propia columna. (3) Responsable, día y franja son una propuesta balanceada (5 entre semana / 5 fin de semana; 5 mañana / 5 tarde; A=4, B=3, C=3). (4) «Verificar» = aún sin fuente externa que lo clasifique como de especialidad: se resuelve antes de salir a campo (ver criterio en Leeme).

Sheet Ficha_Cafe
A1: cafe_id | B1: id_mapa | C1: coordenada | D1: nombre_cafe | E1: localidad | F1: zona_muestreo | G1: tipo_negocio | H1: fecha | I1: dia_tipo | J1: franja | K1: observador | L1: autorizacion_local | M1: st1 | N1: st2 | O1: st3 | P1: st4 | Q1: st5 | R1: st6 | S1: am1 | T1: am2 | U1: am3 | V1: am4 | W1: am5 | X1: am6 | Y1: am7 | Z1: am8 | AA1: idx_story | AB1: idx_amb | AC1: idx_story_10 | AD1: idx_amb_10 | AE1: ficha_completa | AF1: tiene_instagram | AG1: google_rating | AH1: google_resenas | AI1: fotos_ok | AJ1: obs_texto
A2: EJEMPLO | B2: M-000 | D2: Café Ejemplo | E2: Chapinero | F2: Z1 Parkway–Teusaquillo | G2: Independiente (1 local) | H2: 46340 | I2: Fin de semana | J2: Mañana (8–11) | K2: A | L2: 1 | M2: 1 | N2: 1 | O2: 0 | P2: 1 | Q2: 0 | R2: 1 | S2: 1 | T2: 1 | U2: 0 | V2: 1 | W2: 1 | X2: 1 | Y2: 0 | Z2: 1 | AA2: =IF(COUNT(M2:R2)=6,SUM(M2:R2),"") -> 4 | AB2: =IF(COUNT(S2:Z2)=8,SUM(S2:Z2),"") -> 6 | AC2: =IF(AA2="","",AA2/6*10) -> 6.6666667 | AD2: =IF(AB2="","",AB2/8*10) -> 7.5 | AE2: =IF(A2="","",IF(COUNT(M2:Z2)=14,"Completa","Incompleta: "&COUNT(M2:Z2)&" de 14")) -> Completa | AF2: 1 | AG2: 4.6 | AH2: 310 | AI2: 1 | AJ2: Mural con mapa de fincas
A3: C01 | B3: M-01 | C3: 4.631853, -74.073582 | D3: Quipile Café de Origen | E3: Teusaquillo | F3: Z1 Parkway–Teusaquillo | G3: Pequeña cadena (2–5 locales) | K3: A | AA3: =IF(COUNT(M3:R3)=6,SUM(M3:R3),"") | AB3: =IF(COUNT(S3:Z3)=8,SUM(S3:Z3),"") | AC3: =IF(AA3="","",AA3/6*10) | AD3: =IF(AB3="","",AB3/8*10) | AE3: =IF(A3="","",IF(COUNT(M3:Z3)=14,"Completa","Incompleta: "&COUNT(M3:Z3)&" de 14")) -> Incompleta: 0 de 14
A4: C02 | B4: M-02 | C4: 4.628863, -74.072224 | D4: Rolo Café PW | E4: Teusaquillo | F4: Z1 Parkway–Teusaquillo | G4: Independiente (1 local) | K4: B | AA4: =IF(COUNT(M4:R4)=6,SUM(M4:R4),"") | AB4: =IF(COUNT(S4:Z4)=8,SUM(S4:Z4),"") | AC4: =IF(AA4="","",AA4/6*10) | AD4: =IF(AB4="","",AB4/8*10) | AE4: =IF(A4="","",IF(COUNT(M4:Z4)=14,"Completa","Incompleta: "&COUNT(M4:Z4)&" de 14")) -> Incompleta: 0 de 14
A5: C03 | B5: M-03 | C5: 4.622475, -74.070058 | D5: Bogotá Coffee Roasters LAB CINE Y CAFÉ | E5: Teusaquillo | F5: Z1 Parkway–Teusaquillo | G5: Independiente (1 local) | K5: C | AA5: =IF(COUNT(M5:R5)=6,SUM(M5:R5),"") | AB5: =IF(COUNT(S5:Z5)=8,SUM(S5:Z5),"") | AC5: =IF(AA5="","",AA5/6*10) | AD5: =IF(AB5="","",AB5/8*10) | AE5: =IF(A5="","",IF(COUNT(M5:Z5)=14,"Completa","Incompleta: "&COUNT(M5:Z5)&" de 14")) -> Incompleta: 0 de 14
A6: C04 | B6: M-04 | C6: 4.628731, -74.075306 | D6: El Bourbon Café | E6: Teusaquillo | F6: Z1 Parkway–Teusaquillo | G6: Independiente (1 local) | K6: A | AA6: =IF(COUNT(M6:R6)=6,SUM(M6:R6),"") | AB6: =IF(COUNT(S6:Z6)=8,SUM(S6:Z6),"") | AC6: =IF(AA6="","",AA6/6*10) | AD6: =IF(AB6="","",AB6/8*10) | AE6: =IF(A6="","",IF(COUNT(M6:Z6)=14,"Completa","Incompleta: "&COUNT(M6:Z6)&" de 14")) -> Incompleta: 0 de 14
A7: C05 | B7: M-05 | C7: 4.626248, -74.071168 | D7: Ezcarlata Café | E7: Teusaquillo | F7: Z1 Parkway–Teusaquillo | G7: Independiente (1 local) | K7: B | AA7: =IF(COUNT(M7:R7)=6,SUM(M7:R7),"") | AB7: =IF(COUNT(S7:Z7)=8,SUM(S7:Z7),"") | AC7: =IF(AA7="","",AA7/6*10) | AD7: =IF(AB7="","",AB7/8*10) | AE7: =IF(A7="","",IF(COUNT(M7:Z7)=14,"Completa","Incompleta: "&COUNT(M7:Z7)&" de 14")) -> Incompleta: 0 de 14
A8: C06 | B8: M-06 | C8: 4.628678, -74.075199 | D8: Orilla Tienda de Café | E8: Teusaquillo | F8: Z1 Parkway–Teusaquillo | G8: Independiente (1 local) | K8: C | AA8: =IF(COUNT(M8:R8)=6,SUM(M8:R8),"") | AB8: =IF(COUNT(S8:Z8)=8,SUM(S8:Z8),"") | AC8: =IF(AA8="","",AA8/6*10) | AD8: =IF(AB8="","",AB8/8*10) | AE8: =IF(A8="","",IF(COUNT(M8:Z8)=14,"Completa","Incompleta: "&COUNT(M8:Z8)&" de 14")) -> Incompleta: 0 de 14
A9: C07 | B9: M-07 | C9: 4.613318, -74.067341 | D9: CatCoffee | E9: Teusaquillo | F9: Z2 La Macarena | G9: Pequeña cadena (2–5 locales) | K9: A | AA9: =IF(COUNT(M9:R9)=6,SUM(M9:R9),"") | AB9: =IF(COUNT(S9:Z9)=8,SUM(S9:Z9),"") | AC9: =IF(AA9="","",AA9/6*10) | AD9: =IF(AB9="","",AB9/8*10) | AE9: =IF(A9="","",IF(COUNT(M9:Z9)=14,"Completa","Incompleta: "&COUNT(M9:Z9)&" de 14")) -> Incompleta: 0 de 14
A10: C08 | B10: M-08 | C10: 4.616315, -74.071428 | D10: Oishii Bubble Tea At 7 Days | E10: Santa Fe | F10: Z2 La Macarena | G10: Independiente (1 local) | K10: B | AA10: =IF(COUNT(M10:R10)=6,SUM(M10:R10),"") | AB10: =IF(COUNT(S10:Z10)=8,SUM(S10:Z10),"") | AC10: =IF(AA10="","",AA10/6*10) | AD10: =IF(AB10="","",AB10/8*10) | AE10: =IF(A10="","",IF(COUNT(M10:Z10)=14,"Completa","Incompleta: "&COUNT(M10:Z10)&" de 14")) -> Incompleta: 0 de 14
A11: C09 | B11: M-09 | C11: 4.597011, -74.076033 | D11: Arte y Pasión Café | E11: La Candelaria | F11: Z3 Centro | G11: Pequeña cadena (2–5 locales) | K11: C | AA11: =IF(COUNT(M11:R11)=6,SUM(M11:R11),"") | AB11: =IF(COUNT(S11:Z11)=8,SUM(S11:Z11),"") | AC11: =IF(AA11="","",AA11/6*10) | AD11: =IF(AB11="","",AB11/8*10) | AE11: =IF(A11="","",IF(COUNT(M11:Z11)=14,"Completa","Incompleta: "&COUNT(M11:Z11)&" de 14")) -> Incompleta: 0 de 14
A12: C10 | B12: M-10 | C12: 4.600645, -74.073289 | D12: Nossa Café Pastel | E12: La Candelaria | F12: Z3 Centro | G12: Independiente (1 local) | K12: A | AA12: =IF(COUNT(M12:R12)=6,SUM(M12:R12),"") | AB12: =IF(COUNT(S12:Z12)=8,SUM(S12:Z12),"") | AC12: =IF(AA12="","",AA12/6*10) | AD12: =IF(AB12="","",AB12/8*10) | AE12: =IF(A12="","",IF(COUNT(M12:Z12)=14,"Completa","Incompleta: "&COUNT(M12:Z12)&" de 14")) -> Incompleta: 0 de 14
A13: R1 | B13: R-01 | C13: 4.625624, -74.070087 | D13: Filtrando Café | E13: Teusaquillo | F13: Z1 Parkway–Teusaquillo | G13: Independiente (1 local) | K13: B
A14: R2 | B14: R-02 | C14: 4.615197, -74.071853 | D14: Terracota Café y Más | E14: Teusaquillo | F14: Z2 La Macarena | G14: Pequeña cadena (2–5 locales) | K14: C | AA14: =IF(COUNT(M14:R14)=6,SUM(M14:R14),"") | AB14: =IF(COUNT(S14:Z14)=8,SUM(S14:Z14),"") | AC14: =IF(AA14="","",AA14/6*10) | AD14: =IF(AB14="","",AB14/8*10) | AE14: =IF(A14="","",IF(COUNT(M14:Z14)=14,"Completa","Incompleta: "&COUNT(M14:Z14)&" de 14")) -> Incompleta: 0 de 14
A15: R3 | B15: R-03 | C15: 4.598687, -74.069792 | D15: Café Nos | E15: La Candelaria | F15: Z3 Centro | G15: Independiente (1 local) | K15: A | AA15: =IF(COUNT(M15:R15)=6,SUM(M15:R15),"") | AB15: =IF(COUNT(S15:Z15)=8,SUM(S15:Z15),"") | AC15: =IF(AA15="","",AA15/6*10) | AD15: =IF(AB15="","",AB15/8*10) | AE15: =IF(A15="","",IF(COUNT(M15:Z15)=14,"Completa","Incompleta: "&COUNT(M15:Z15)&" de 14")) -> Incompleta: 0 de 14
AA16: =IF(COUNT(M16:R16)=6,SUM(M16:R16),"") | AB16: =IF(COUNT(S16:Z16)=8,SUM(S16:Z16),"") | AC16: =IF(AA16="","",AA16/6*10) | AD16: =IF(AB16="","",AB16/8*10) | AE16: =IF(A16="","",IF(COUNT(M16:Z16)=14,"Completa","Incompleta: "&COUNT(M16:Z16)&" de 14"))
AA17: =IF(COUNT(M17:R17)=6,SUM(M17:R17),"") | AB17: =IF(COUNT(S17:Z17)=8,SUM(S17:Z17),"") | AC17: =IF(AA17="","",AA17/6*10) | AD17: =IF(AB17="","",AB17/8*10) | AE17: =IF(A17="","",IF(COUNT(M17:Z17)=14,"Completa","Incompleta: "&COUNT(M17:Z17)&" de 14"))
AA18: =IF(COUNT(M18:R18)=6,SUM(M18:R18),"") | AB18: =IF(COUNT(S18:Z18)=8,SUM(S18:Z18),"") | AC18: =IF(AA18="","",AA18/6*10) | AD18: =IF(AB18="","",AB18/8*10) | AE18: =IF(A18="","",IF(COUNT(M18:Z18)=14,"Completa","Incompleta: "&COUNT(M18:Z18)&" de 14"))
AA19: =IF(COUNT(M19:R19)=6,SUM(M19:R19),"") | AB19: =IF(COUNT(S19:Z19)=8,SUM(S19:Z19),"") | AC19: =IF(AA19="","",AA19/6*10) | AD19: =IF(AB19="","",AB19/8*10) | AE19: =IF(A19="","",IF(COUNT(M19:Z19)=14,"Completa","Incompleta: "&COUNT(M19:Z19)&" de 14"))
AA20: =IF(COUNT(M20:R20)=6,SUM(M20:R20),"") | AB20: =IF(COUNT(S20:Z20)=8,SUM(S20:Z20),"") | AC20: =IF(AA20="","",AA20/6*10) | AD20: =IF(AB20="","",AB20/8*10) | AE20: =IF(A20="","",IF(COUNT(M20:Z20)=14,"Completa","Incompleta: "&COUNT(M20:Z20)&" de 14"))
AA21: =IF(COUNT(M21:R21)=6,SUM(M21:R21),"") | AB21: =IF(COUNT(S21:Z21)=8,SUM(S21:Z21),"") | AC21: =IF(AA21="","",AA21/6*10) | AD21: =IF(AB21="","",AB21/8*10) | AE21: =IF(A21="","",IF(COUNT(M21:Z21)=14,"Completa","Incompleta: "&COUNT(M21:Z21)&" de 14"))
AA22: =IF(COUNT(M22:R22)=6,SUM(M22:R22),"") | AB22: =IF(COUNT(S22:Z22)=8,SUM(S22:Z22),"") | AC22: =IF(AA22="","",AA22/6*10) | AD22: =IF(AB22="","",AB22/8*10) | AE22: =IF(A22="","",IF(COUNT(M22:Z22)=14,"Completa","Incompleta: "&COUNT(M22:Z22)&" de 14"))
AA23: =IF(COUNT(M23:R23)=6,SUM(M23:R23),"") | AB23: =IF(COUNT(S23:Z23)=8,SUM(S23:Z23),"") | AC23: =IF(AA23="","",AA23/6*10) | AD23: =IF(AB23="","",AB23/8*10) | AE23: =IF(A23="","",IF(COUNT(M23:Z23)=14,"Completa","Incompleta: "&COUNT(M23:Z23)&" de 14"))
AA24: =IF(COUNT(M24:R24)=6,SUM(M24:R24),"") | AB24: =IF(COUNT(S24:Z24)=8,SUM(S24:Z24),"") | AC24: =IF(AA24="","",AA24/6*10) | AD24: =IF(AB24="","",AB24/8*10) | AE24: =IF(A24="","",IF(COUNT(M24:Z24)=14,"Completa","Incompleta: "&COUNT(M24:Z24)&" de 14"))
AA25: =IF(COUNT(M25:R25)=6,SUM(M25:R25),"") | AB25: =IF(COUNT(S25:Z25)=8,SUM(S25:Z25),"") | AC25: =IF(AA25="","",AA25/6*10) | AD25: =IF(AB25="","",AB25/8*10) | AE25: =IF(A25="","",IF(COUNT(M25:Z25)=14,"Completa","Incompleta: "&COUNT(M25:Z25)&" de 14"))
AA26: =IF(COUNT(M26:R26)=6,SUM(M26:R26),"") | AB26: =IF(COUNT(S26:Z26)=8,SUM(S26:Z26),"") | AC26: =IF(AA26="","",AA26/6*10) | AD26: =IF(AB26="","",AB26/8*10) | AE26: =IF(A26="","",IF(COUNT(M26:Z26)=14,"Completa","Incompleta: "&COUNT(M26:Z26)&" de 14"))
AA27: =IF(COUNT(M27:R27)=6,SUM(M27:R27),"") | AB27: =IF(COUNT(S27:Z27)=8,SUM(S27:Z27),"") | AC27: =IF(AA27="","",AA27/6*10) | AD27: =IF(AB27="","",AB27/8*10) | AE27: =IF(A27="","",IF(COUNT(M27:Z27)=14,"Completa","Incompleta: "&COUNT(M27:Z27)&" de 14"))
... AA31: =IF(COUNT(M31:R31)=6,SUM(M31:R31),"") | AB31: =IF(COUNT(S31:Z31)=8,SUM(S31:Z31),"") | AC31: =IF(AA31="","",AA31/6*10) | AD31: =IF(AB31="","",AB31/8*10) | AE31: =IF(A31="","",IF(COUNT(M31:Z31)=14,"Completa","Incompleta: "&COUNT(M31:Z31)&" de 14"))

Sheet Encuestas
A1: enc_id | B1: cafe_id | C1: fecha | D1: hora | E1: encuestador | F1: consentimiento | G1: freq_visita | H1: motivo_visita | I1: como_conocio | J1: minutos_permanencia | K1: per_ambiente | L1: per_distintivo | M1: per_origen | N1: per_historia | O1: per_calidad | P1: per_atencion | Q1: per_descripcion | R1: recuerda_dato | S1: nps_recomienda | T1: prob_volver | U1: n_otros_cafes | V1: primera_opcion | W1: obs_encuestador
A2: EJEMPLO | B2: EJEMPLO | C2: 46340 | D2: 09:40 | E2: A | F2: 1 | G2: 1–3 veces al mes | H2: Reunión social | I2: Redes sociales | J2: 60 | K2: 5 | L2: 4 | M2: 3 | N2: NA | O2: 5 | P2: 4 | R2: 0 | S2: 9 | T2: 5 | U2: 1–2 | V2: Una de varias opciones | W2: Ejemplo de formato: «NA» = no conoce la historia

Sheet Avance
A1: cafe_id | B1: encuestas_hechas | C1: meta | D1: % avance | E1: ficha_lista | F1: idx_story | G1: idx_amb
A2: =Muestra_Cafes!A2 -> C01 | B2: =COUNTIFS(Encuestas!$B$3:$B$200,A2,Encuestas!$F$3:$F$200,1) -> 0 | C2: =Muestra_Cafes!M2 -> 8 | D2: =IF(C2=0,"",MIN(1,B2/C2)) -> 0 | E2: =IF(COUNTIF(Ficha_Cafe!$A$3:$A$31,A2)>0,"Sí","No") -> Sí | F2: {=IFERROR(INDEX(Ficha_Cafe!$AA$3:$AA$31,MATCH(A2,Ficha_Cafe!$A$3:$A$31,0)),"")} | G2: {=IFERROR(INDEX(Ficha_Cafe!$AB$3:$AB$31,MATCH(A2,Ficha_Cafe!$A$3:$A$31,0)),"")}
A3: =Muestra_Cafes!A3 -> C02 | B3: =COUNTIFS(Encuestas!$B$3:$B$200,A3,Encuestas!$F$3:$F$200,1) -> 0 | C3: =Muestra_Cafes!M3 -> 8 | D3: =IF(C3=0,"",MIN(1,B3/C3)) -> 0 | E3: =IF(COUNTIF(Ficha_Cafe!$A$3:$A$31,A3)>0,"Sí","No") -> Sí | F3: {=IFERROR(INDEX(Ficha_Cafe!$AA$3:$AA$31,MATCH(A3,Ficha_Cafe!$A$3:$A$31,0)),"")} | G3: {=IFERROR(INDEX(Ficha_Cafe!$AB$3:$AB$31,MATCH(A3,Ficha_Cafe!$A$3:$A$31,0)),"")}
A4: =Muestra_Cafes!A4 -> C03 | B4: =COUNTIFS(Encuestas!$B$3:$B$200,A4,Encuestas!$F$3:$F$200,1) -> 0 | C4: =Muestra_Cafes!M4 -> 8 | D4: =IF(C4=0,"",MIN(1,B4/C4)) -> 0 | E4: =IF(COUNTIF(Ficha_Cafe!$A$3:$A$31,A4)>0,"Sí","No") -> Sí | F4: {=IFERROR(INDEX(Ficha_Cafe!$AA$3:$AA$31,MATCH(A4,Ficha_Cafe!$A$3:$A$31,0)),"")} | G4: {=IFERROR(INDEX(Ficha_Cafe!$AB$3:$AB$31,MATCH(A4,Ficha_Cafe!$A$3:$A$31,0)),"")}
A5: =Muestra_Cafes!A5 -> C04 | B5: =COUNTIFS(Encuestas!$B$3:$B$200,A5,Encuestas!$F$3:$F$200,1) -> 0 | C5: =Muestra_Cafes!M5 -> 8 | D5: =IF(C5=0,"",MIN(1,B5/C5)) -> 0 | E5: =IF(COUNTIF(Ficha_Cafe!$A$3:$A$31,A5)>0,"Sí","No") -> Sí | F5: {=IFERROR(INDEX(Ficha_Cafe!$AA$3:$AA$31,MATCH(A5,Ficha_Cafe!$A$3:$A$31,0)),"")} | G5: {=IFERROR(INDEX(Ficha_Cafe!$AB$3:$AB$31,MATCH(A5,Ficha_Cafe!$A$3:$A$31,0)),"")}
A6: =Muestra_Cafes!A6 -> C05 | B6: =COUNTIFS(Encuestas!$B$3:$B$200,A6,Encuestas!$F$3:$F$200,1) -> 0 | C6: =Muestra_Cafes!M6 -> 8 | D6: =IF(C6=0,"",MIN(1,B6/C6)) -> 0 | E6: =IF(COUNTIF(Ficha_Cafe!$A$3:$A$31,A6)>0,"Sí","No") -> Sí | F6: {=IFERROR(INDEX(Ficha_Cafe!$AA$3:$AA$31,MATCH(A6,Ficha_Cafe!$A$3:$A$31,0)),"")} | G6: {=IFERROR(INDEX(Ficha_Cafe!$AB$3:$AB$31,MATCH(A6,Ficha_Cafe!$A$3:$A$31,0)),"")}
A7: =Muestra_Cafes!A7 -> C06 | B7: =COUNTIFS(Encuestas!$B$3:$B$200,A7,Encuestas!$F$3:$F$200,1) -> 0 | C7: =Muestra_Cafes!M7 -> 8 | D7: =IF(C7=0,"",MIN(1,B7/C7)) -> 0 | E7: =IF(COUNTIF(Ficha_Cafe!$A$3:$A$31,A7)>0,"Sí","No") -> Sí | F7: {=IFERROR(INDEX(Ficha_Cafe!$AA$3:$AA$31,MATCH(A7,Ficha_Cafe!$A$3:$A$31,0)),"")} | G7: {=IFERROR(INDEX(Ficha_Cafe!$AB$3:$AB$31,MATCH(A7,Ficha_Cafe!$A$3:$A$31,0)),"")}
A8: =Muestra_Cafes!A8 -> C07 | B8: =COUNTIFS(Encuestas!$B$3:$B$200,A8,Encuestas!$F$3:$F$200,1) -> 0 | C8: =Muestra_Cafes!M8 -> 8 | D8: =IF(C8=0,"",MIN(1,B8/C8)) -> 0 | E8: =IF(COUNTIF(Ficha_Cafe!$A$3:$A$31,A8)>0,"Sí","No") -> Sí | F8: {=IFERROR(INDEX(Ficha_Cafe!$AA$3:$AA$31,MATCH(A8,Ficha_Cafe!$A$3:$A$31,0)),"")} | G8: {=IFERROR(INDEX(Ficha_Cafe!$AB$3:$AB$31,MATCH(A8,Ficha_Cafe!$A$3:$A$31,0)),"")}
A9: =Muestra_Cafes!A9 -> C08 | B9: =COUNTIFS(Encuestas!$B$3:$B$200,A9,Encuestas!$F$3:$F$200,1) -> 0 | C9: =Muestra_Cafes!M9 -> 8 | D9: =IF(C9=0,"",MIN(1,B9/C9)) -> 0 | E9: =IF(COUNTIF(Ficha_Cafe!$A$3:$A$31,A9)>0,"Sí","No") -> Sí | F9: {=IFERROR(INDEX(Ficha_Cafe!$AA$3:$AA$31,MATCH(A9,Ficha_Cafe!$A$3:$A$31,0)),"")} | G9: {=IFERROR(INDEX(Ficha_Cafe!$AB$3:$AB$31,MATCH(A9,Ficha_Cafe!$A$3:$A$31,0)),"")}
A10: =Muestra_Cafes!A10 -> C09 | B10: =COUNTIFS(Encuestas!$B$3:$B$200,A10,Encuestas!$F$3:$F$200,1) -> 0 | C10: =Muestra_Cafes!M10 -> 8 | D10: =IF(C10=0,"",MIN(1,B10/C10)) -> 0 | E10: =IF(COUNTIF(Ficha_Cafe!$A$3:$A$31,A10)>0,"Sí","No") -> Sí | F10: {=IFERROR(INDEX(Ficha_Cafe!$AA$3:$AA$31,MATCH(A10,Ficha_Cafe!$A$3:$A$31,0)),"")} | G10: {=IFERROR(INDEX(Ficha_Cafe!$AB$3:$AB$31,MATCH(A10,Ficha_Cafe!$A$3:$A$31,0)),"")}
A11: =Muestra_Cafes!A11 -> C10 | B11: =COUNTIFS(Encuestas!$B$3:$B$200,A11,Encuestas!$F$3:$F$200,1) -> 0 | C11: =Muestra_Cafes!M11 -> 8 | D11: =IF(C11=0,"",MIN(1,B11/C11)) -> 0 | E11: =IF(COUNTIF(Ficha_Cafe!$A$3:$A$31,A11)>0,"Sí","No") -> Sí | F11: {=IFERROR(INDEX(Ficha_Cafe!$AA$3:$AA$31,MATCH(A11,Ficha_Cafe!$A$3:$A$31,0)),"")} | G11: {=IFERROR(INDEX(Ficha_Cafe!$AB$3:$AB$31,MATCH(A11,Ficha_Cafe!$A$3:$A$31,0)),"")}
A12: =Muestra_Cafes!A12 -> R1 | B12: =COUNTIFS(Encuestas!$B$3:$B$200,A12,Encuestas!$F$3:$F$200,1) -> 0 | C12: =Muestra_Cafes!M12 -> 0 | D12: =IF(C12=0,"",MIN(1,B12/C12)) | E12: =IF(COUNTIF(Ficha_Cafe!$A$3:$A$31,A12)>0,"Sí","No") -> Sí | F12: {=IFERROR(INDEX(Ficha_Cafe!$AA$3:$AA$31,MATCH(A12,Ficha_Cafe!$A$3:$A$31,0)),"")} | G12: {=IFERROR(INDEX(Ficha_Cafe!$AB$3:$AB$31,MATCH(A12,Ficha_Cafe!$A$3:$A$31,0)),"")}
A13: =Muestra_Cafes!A13 -> R2 | B13: =COUNTIFS(Encuestas!$B$3:$B$200,A13,Encuestas!$F$3:$F$200,1) -> 0 | C13: =Muestra_Cafes!M13 -> 0 | D13: =IF(C13=0,"",MIN(1,B13/C13)) | E13: =IF(COUNTIF(Ficha_Cafe!$A$3:$A$31,A13)>0,"Sí","No") -> Sí | F13: {=IFERROR(INDEX(Ficha_Cafe!$AA$3:$AA$31,MATCH(A13,Ficha_Cafe!$A$3:$A$31,0)),"")} | G13: {=IFERROR(INDEX(Ficha_Cafe!$AB$3:$AB$31,MATCH(A13,Ficha_Cafe!$A$3:$A$31,0)),"")}
... A15: =Muestra_Cafes!A15 | B15: =COUNTIFS(Encuestas!$B$3:$B$200,A15,Encuestas!$F$3:$F$200,1) -> 0 | C15: =Muestra_Cafes!M15 -> 0 | D15: =IF(C15=0,"",MIN(1,B15/C15)) | E15: =IF(COUNTIF(Ficha_Cafe!$A$3:$A$31,A15)>0,"Sí","No") -> No | F15: {=IFERROR(INDEX(Ficha_Cafe!$AA$3:$AA$31,MATCH(A15,Ficha_Cafe!$A$3:$A$31,0)),"")} | G15: {=IFERROR(INDEX(Ficha_Cafe!$AB$3:$AB$31,MATCH(A15,Ficha_Cafe!$A$3:$A$31,0)),"")}
A16: TOTAL | B16: =SUM(B2:B15) -> 0 | C16: =SUM(C2:C15) -> 80 | D16: =IF(C16=0,"",MIN(1,B16/C16)) -> 0 | E16: =COUNTIFS(E2:E15,"Sí",C2:C15,">0")&" de "&COUNTIF(C2:C15,">0")&" fichas" -> 10 de 10 fichas
A18: Meta: 10 cafés × 8 encuestas = 80. Si se activa una reserva (R1–R4), ponga meta 0 y estado «Reemplazado» al local original en Muestra_Cafes, y meta 8 y estado «Pendiente» a la reserva: el total sigue en 80.

Sheet Piloto
A1: FFicha cafe
A2: cafe_id | B2: id_mapa | C2: coordenada | D2: nombre_cafe | E2: localidad | F2: zona_muestreo | G2: tipo_negocio | H2: fecha | I2: dia_tipo | J2: franja | K2: observador | L2: autorizacion_local | M2: st1 | N2: st2 | O2: st3 | P2: st4 | Q2: st5 | R2: st6 | S2: am1 | T2: am2 | U2: am3 | V2: am4 | W2: am5 | X2: am6 | Y2: am7 | Z2: am8 | AA2: tiene_instagram | AB2: google_rating | AC2: google_resenas | AD2: fotos_ok | AE2: obs_texto
A3: R2 | B3: R-02 | C3: 74.0703567,4.6159643,0 | D3: Terracota Café y Más | E3: Z2 La Macarena | F3: Teusaquillo | G3: Pequeña cadena (2–5 locales) | H3: 46323 | I3: Entre semana | J3: Tarde (14–17) | K3: A | L3: 1 | M3: 1 | N3: 1 | O3: 1 | P3: 1 | Q3: 1 | R3: 1 | S3: 1 | T3: 1 | U3: 0 | V3: 0 | W3: 1 | X3: 1 | Y3: 0 | Z3: 1 | AA3: 1 | AB3: 4.8 | AC3: 168 | AD3: 1 | AE3: El sitio se ve comodo, buena iluminacion.
A4: Encuestas
A5: enc_id | B5: cafe_id | C5: fecha | D5: hora | E5: encuestador | F5: consentimiento | G5: freq_visita | H5: motivo_visita | I5: como_conocio | J5: minutos_permanencia | K5: per_ambiente | L5: per_distintivo | M5: per_origen | N5: per_historia | O5: per_calidad | P5: per_atencion | Q5: per_descripcion | R5: recuerda_dato | S5: nps_recomienda | T5: prob_volver | U5: n_otros_cafes | V5: primera_opcion | W5: obs_encuestador
A6: P0-1 | B6: R2 | C6: 46323 | D6: 0.16666667 | E6: A | F6: 1 | G6: Primera vez | H6: Probar cafe de especialidad | I6: Google maps u otra app | J6: 30-60 minutos | K6: 4 | L6: 4 | M6: 1 | N6: 4 | O6: 1 | P6: 4 | Q6: 1 | R6: 1 | S6: 6 | T6: 3 | U6: 3 a 5 | V6: Una de varias opciones | W6: Ninguna
A7: Observaciones
A8: TIEMPO QUE TOMO RESOLVER LA FICHA: | B8: 5 min aprox | C8: TIEMPO QUE TOMO RESOLVER LA ENCUESTA: | D8: 0.055555556

Sheet Diccionario
A1: variable | B1: hoja | C1: bloque | D1: pregunta o ítem | E1: tipo | F1: valores permitidos | G1: obligatoria | H1: uso en el análisis
A2: cafe_id | B2: Ficha_Cafe | C2: Identificación | D2: ID único del café (C01–C10; P1–P2 piloto; R1–R4 reemplazos) | E2: texto | F2: libre | G2: Sí | H2: Llave de unión con Encuestas (unidad de análisis: el café)
A3: id_mapa | B3: Ficha_Cafe | C3: Identificación | D3: ID del café en el shapefile de la Entrega 3a (no la dirección) | E3: texto | F3: libre | G3: Sí | H3: Unión con el mapa y los análisis espaciales
A4: nombre_cafe | B4: Ficha_Cafe | C4: Identificación | D4: Nombre del negocio | E4: texto | F4: libre | G4: Sí | H4: Identificación (único dato nominal)
A5: localidad | B5: Ficha_Cafe | C5: Identificación | D5: Localidad donde está el café | E5: categórica | F5: Chapinero | Usaquén | Teusaquillo | Barrios Unidos | Santa Fe | La Candelaria | Suba | Otra | G5: Sí | H5: Descriptivo / control
A6: zona_muestreo | B6: Ficha_Cafe | C6: Identificación | D6: Estrato geográfico del muestreo | E6: categórica | F6: Z1 Parkway–Teusaquillo | Z2 La Macarena | Z3 Centro | G6: Sí | H6: Comparaciones por zona
A7: tipo_negocio | B7: Ficha_Cafe | C7: Identificación | D7: Tipo de negocio | E7: categórica | F7: Independiente (1 local) | Pequeña cadena (2–5 locales) | Cadena grande (6+ locales) | Tostadora con cafetería | G7: Sí | H7: Control / comparación por modelo de negocio
A8: fecha | B8: Ficha_Cafe | C8: Identificación | D8: Fecha de la visita | E8: fecha | F8: libre | G8: Sí | H8: Control de campo
A9: dia_tipo | B9: Ficha_Cafe | C9: Identificación | D9: Tipo de día | E9: categórica | F9: Entre semana | Fin de semana | G9: Sí | H9: Control (afluencia y perfil de clientes)
A10: franja | B10: Ficha_Cafe | C10: Identificación | D10: Franja horaria de la visita | E10: categórica | F10: Mañana (8–11) | Tarde (14–17) | G10: Sí | H10: Control
A11: observador | B11: Ficha_Cafe | C11: Identificación | D11: Quién llenó la ficha (A, B o C) | E11: categórica | F11: A | B | C | G11: Sí | H11: Control de calidad / acuerdo entre observadores
A12: autorizacion_local | B12: Ficha_Cafe | C12: Identificación | D12: El administrador autorizó la visita y las fotos del espacio (1 = sí) | E12: binaria | F12: 1 = sí · 0 = no | G12: Sí | H12: Control ético; activa reemplazos
... A58: obs_encuestador | B58: Encuestas | C58: Cierre | D58: Observaciones del encuestador (dudas, interrupciones, preguntas no respondidas) | E58: texto | F58: libre | G58: No | H58: Control de calidad / informe de campo

Sheet Listas
A1: localidad | B1: zona_muestreo | C1: tipo_negocio | D1: dia_tipo | E1: franja | F1: persona | G1: freq_visita | H1: motivo_visita | I1: como_conocio | J1: factor | K1: n_otros_cafes | L1: primera_opcion | M1: estado_muestra
A2: Chapinero | B2: Z1 Parkway–Teusaquillo | C2: Independiente (1 local) | D2: Entre semana | E2: Mañana (8–11) | F2: A | G2: Primera vez | H2: Trabajo o estudio | I2: Redes sociales | J2: Calidad del café | K2: Ninguno | L2: Es mi primera opción | M2: Pendiente
A3: Usaquén | B3: Z2 La Macarena | C3: Pequeña cadena (2–5 locales) | D3: Fin de semana | E3: Tarde (14–17) | F3: B | G3: Menos de 1 vez al mes | H3: Reunión social | I3: Recomendación | J3: Ambiente | K3: 1 a 2 | L3: Una de varias opciones | M3: Visitado
A4: Teusaquillo | B4: Z3 Centro | C4: Cadena grande (6+ locales) | F4: C | G4: 1–3 veces al mes | H4: Probar café de especialidad | I4: Pasó por el lugar | J4: Historia y origen | K4: 3 a 5 | L4: Vine por esta vez | M4: Reemplazado
A5: Barrios Unidos | C5: Tostadora con cafetería | G5: Semanal o más | H5: Pausa rápida o rutina | I5: Google Maps u otra app | J5: Atención | K5: 6 o más | M5: Piloto
A6: Santa Fe | H6: Otro | I6: Otro | J6: Precio | M6: Reserva
A7: La Candelaria | J7: Ubicación
A8: Suba | J8: Redes sociales
A9: Otra
